zenity/__init__.py
zenity_py-1.0.7.dist-info/METADATA
zenity_py-1.0.7.dist-info/WHEEL
zenity_py-1.0.7.dist-info/top_level.txt
zenity_py-1.0.7.dist-info/RECORD
