Metadata-Version: 2.1
Name: zenity_py
Version: 1.0.7
Summary: A Python library for the CLI tool zenity.
Home-page: https://github.com/Marko2155/zenity_py
Author: Marko Camandioti
Author-email: camandiotimarko@gmail.com
License: MIT
Project-URL: Documentation, https://github.com/Marko2155/zenity_py#readme
Project-URL: Source, https://github.com/Marko2155/zenity_py
Project-URL: Tracker, https://github.com/Marko2155/zenity_py/issues
Keywords: zenity
